{
  "packageRules": [
    {
      "groupName": "androidx.lifecycle",
      "packagePatterns": [
        "^androidx\\.lifecycle:"
      ]
    },
    {
      "groupName": "androidx.navigation",
      "packagePatterns": [
        "^androidx\\.navigation:"
      ]
    },
    {
      "groupName": "androidx.room",
      "packagePatterns": [
        "^androidx\\.room:"
      ]
    },
    {
      "groupName": "androidx.test",
      "packagePatterns": [
        "^androidx\\.test:",
        "^androidx\\.test\\.ext:",
        "^androidx\\.test\\.espresso:"
      ]
    },
    {
      "groupName": "AssistedInject",
      "packagePatterns": [
        "^com\\.squareup\\.inject:"
      ]
    },
    {
      "groupName": "AutoDispose",
      "packagePatterns": [
        "^com\\.uber\\.autodispose:autodispose"
      ]
    },
    {
      "groupName": "Dagger",
      "packagePatterns": [
        "^com\\.google\\.dagger:dagger"
      ]
    },
    {
      "groupName": "Dart and Henson",
      "packagePatterns": [
        "^com\\.f2prateek\\.dart:"
      ]
    },
    {
      "groupName": "Epoxy",
      "packagePatterns": [
        "^com\\.airbnb\\.android:epoxy"
      ]
    },
    {
      "groupName": "Fabric and Crashlytics",
      "packageNames": [
        "io.fabric.tools:gradle",
        "com.crashlytics.sdk.android:crashlytics"
      ]
    },
    {
      "groupName": "Firebase",
      "packageNames": [
        "com.google.android.gms:play-services-tagmanager"
      ],
      "packagePatterns": [
        "^com\\.google\\.firebase:"
      ]
    },
    {
      "groupName": "Flipper",
      "packagePatterns": [
        "^com\\.facebook\\.flipper:",
        "^com\\.facebook\\.soloader:soloader"
      ],
      "automerge": true
    },
    {
      "groupName": "Glide",
      "packagePatterns": [
        "^com\\.github\\.bumptech\\.glide:"
      ]
    },
    {
      "groupName": "Groupie",
      "packagePatterns": [
        "^com\\.xwray:groupie"
      ]
    },
    {
      "groupName": "Hyperion",
      "packagePatterns": [
        "^com\\.willowtreeapps\\.hyperion:"
      ]
    },
    {
      "groupName": "Jetpack Compose",
      "packagePatterns": [
        "^androidx\\.compose:",
        "^androidx\\.compose\\.animation:",
        "^androidx\\.compose\\.compiler:",
        "^androidx\\.compose\\.foundation:",
        "^androidx\\.compose\\.material:",
        "^androidx\\.compose\\.runtime:",
        "^androidx\\.compose\\.ui:"
      ]
    },
    {
      "groupName": "Kotlin",
      "packagePatterns": [
        "^org\\.jetbrains\\.kotlin:"
      ]
    },
    {
      "groupName": "kotlinx.coroutines",
      "packagePatterns": [
        "^org\\.jetbrains\\.kotlinx:kotlinx-coroutines"
      ]
    },
    {
      "groupName": "LeakCanary",
      "packagePatterns": [
        "^com\\.squareup\\.leakcanary:"
      ]
    },
    {
      "groupName": "MockK",
      "packagePatterns": [
        "^io\\.mockk:mockk"
      ]
    },
    {
      "groupName": "Moshi",
      "packagePatterns": [
        "^com\\.squareup\\.moshi:"
      ]
    },
    {
      "groupName": "OkHttp",
      "packagePatterns": [
        "^com\\.squareup\\.okhttp3:"
      ]
    },
    {
      "groupName": "PaperParcel",
      "packagePatterns": [
        "^nz\\.bradcampbell:paperparcel"
      ]
    },
    {
      "groupName": "Play Services",
      "packagePatterns": [
        "^com\\.google\\.android\\.gms:play-services-"
      ]
    },
    {
      "groupName": "Realm",
      "packagePatterns": [
        "^io\\.realm:realm"
      ]
    },
    {
      "groupName": "Retrofit",
      "packagePatterns": [
        "^com\\.squareup\\.retrofit2:"
      ]
    },
    {
      "groupName": "RxJava 2",
      "packagePatterns": [
        "^io\\.reactivex\\.rxjava2:"
      ]
    },
    {
      "groupName": "RxJava 3",
      "packagePatterns": [
        "^io\\.reactivex\\.rxjava3:"
      ]
    },
    {
      "groupName": "ThreeTenABP",
      "packageNames": [
        "org.threeten:threetenbp",
        "com.jakewharton.threetenabp:threetenabp"
      ]
    }
  ]
}
